src/Topsis-Arunain-102016011.py
Topsis_Arunain_102016011-1.0.0.dist-info/LICENSE.md
Topsis_Arunain_102016011-1.0.0.dist-info/METADATA
Topsis_Arunain_102016011-1.0.0.dist-info/WHEEL
Topsis_Arunain_102016011-1.0.0.dist-info/top_level.txt
Topsis_Arunain_102016011-1.0.0.dist-info/RECORD
