Metadata-Version: 2.1
Name: Topsis-Arunain-102016011
Version: 1.0.0
Summary: A package for topsis score generation.
Author: Arunain
Author-email: aarunain_be20@thapar.edu
License: MIT License        
License-File: LICENSE.md
Requires-Dist: pandas
Requires-Dist: numpy
